datasette_metadata_editable/__init__.py
datasette_metadata_editable/internal_migrations.py
datasette_metadata_editable/static/plugin.js
datasette_metadata_editable/templates/datasette_metadata_editable_edit.html
datasette_metadata_editable-0.2a3.dist-info/licenses/LICENSE
datasette_metadata_editable-0.2a3.dist-info/METADATA
datasette_metadata_editable-0.2a3.dist-info/WHEEL
datasette_metadata_editable-0.2a3.dist-info/entry_points.txt
datasette_metadata_editable-0.2a3.dist-info/top_level.txt
datasette_metadata_editable-0.2a3.dist-info/RECORD
