Metadata-Version: 2.4
Name: datasette-metadata-editable
Version: 0.2a3
Author: Alex Garcia
License-Expression: Apache-2.0
Project-URL: Homepage, https://github.com/datasette/datasette-metadata-editable
Project-URL: Changelog, https://github.com/datasette/datasette-metadata-editable/releases
Project-URL: Issues, https://github.com/datasette/datasette-metadata-editable/issues
Project-URL: CI, https://github.com/datasette/datasette-metadata-editable/actions
Classifier: Framework :: Datasette
Requires-Python: >=3.10
License-File: LICENSE
Requires-Dist: datasette>=1.0a21
Requires-Dist: markdown2>=2.4.10
Requires-Dist: nh3==0.2.14
Requires-Dist: sqlite-migrate>=0.1b0
Provides-Extra: test
Requires-Dist: pytest; extra == "test"
Requires-Dist: pytest-asyncio; extra == "test"
Requires-Dist: ruff; extra == "test"
Requires-Dist: syrupy; extra == "test"
Dynamic: license-file
